runware/__init__.py
runware/async_retry.py
runware/base.py
runware/logging_config.py
runware/reconnection.py
runware/server.py
runware/types.py
runware/utils.py
runware-0.4.41.dist-info/licenses/LICENSE
tests/__init__.py
tests/test_base.py
tests/test_server.py
tests/test_types.py
tests/test_utils.py
runware-0.4.41.dist-info/METADATA
runware-0.4.41.dist-info/WHEEL
runware-0.4.41.dist-info/top_level.txt
runware-0.4.41.dist-info/RECORD
