Metadata-Version: 2.4
Name: runware
Version: 0.4.41
Summary: The Python Runware SDK is used to interact with the Runware API, powered by the Runware inference platform. It supports image generation, video generation, image upscale, video upscale, image caption, video caption, image background removal, video background removal, audio generation, and more. It also allows the use of an existing gallery of models or selecting any model or LoRA from the CivitAI gallery. The API also supports inpainting, outpainting, and a series of other ControlNet mo
Home-page: https://github.com/runware/sdk-python
Author: Runware Inc.
Author-email: python.sdk@runware.ai
License: MIT
Project-URL: Documentation, https://docs.runware.ai/
Project-URL: Changes, https://github.com/runware/sdk-python/releases
Project-URL: Code, https://github.com/runware/sdk-python
Project-URL: Issue tracker, https://github.com/runware/sdk-python/issues
Keywords: Runware,stable diffusion,text to image,image to text,text to video,image to video,video generation,text to audio,audio generation,image upscale,video upscale,background removal
Classifier: Development Status :: 3 - Alpha
Classifier: Intended Audience :: Developers
Classifier: License :: OSI Approved :: MIT License
Classifier: Operating System :: OS Independent
Classifier: Programming Language :: Python :: 3
Classifier: Programming Language :: Python :: 3 :: Only
Classifier: Programming Language :: Python :: 3.10
Classifier: Programming Language :: Python :: 3.11
Classifier: Programming Language :: Python :: 3.12
Requires-Python: >=3.10
License-File: LICENSE
Requires-Dist: aiofiles==23.2.1
Requires-Dist: python-dotenv==1.0.1
Requires-Dist: websockets>=12.0
Dynamic: author
Dynamic: author-email
Dynamic: classifier
Dynamic: description
Dynamic: description-content-type
Dynamic: home-page
Dynamic: keywords
Dynamic: license
Dynamic: license-file
Dynamic: project-url
Dynamic: requires-dist
Dynamic: requires-python
Dynamic: summary
